certificate_check/__init__.py
certificate_check/main.py
certificate_check-1.3.0.dist-info/entry_points.txt
certificate_check-1.3.0.dist-info/METADATA
certificate_check-1.3.0.dist-info/WHEEL
certificate_check-1.3.0.dist-info/RECORD
