Metadata-Version: 2.1
Name: certificate-check
Version: 1.3.0
Summary: 
Author: helio12242
Author-email: heliojorgesilva12@hotmail.com
Requires-Python: >=3.10,<4.0
Classifier: Programming Language :: Python :: 3
Classifier: Programming Language :: Python :: 3.10
Classifier: Programming Language :: Python :: 3.11
Classifier: Programming Language :: Python :: 3.12
Requires-Dist: cryptography (>=43.0.0,<44.0.0)
Requires-Dist: requests (>=2.32.3,<3.0.0)
Requires-Dist: typer (>=0.12.5,<0.13.0)
